[{"url":"https://www.zhihu.com/question/1888613271411582615","title":"微信上线新功能找附近的工作，已覆盖全国超 200 个地市，你看好这个功能吗？会带来哪些便利？"},{"url":"https://www.zhihu.com/question/1888321817753646503","title":"快餐界「爱马仕」被中产抛弃，258 一个的汉堡卖不动了，高端汉堡生意为什么不香了？如何评价这种商业模式？"},{"url":"https://www.zhihu.com/question/15703655592","title":"如何看待蔚来董事长李斌称已赶走 20 多个副总裁？裁高管和一线员工哪个对公司影响更大？"},{"url":"https://www.zhihu.com/question/15339566033","title":"黄金还会涨多久？"},{"url":"https://www.zhihu.com/question/15739608236","title":"韩国东南部大型山火已造成 26 人死亡，目前灭火进展如何？有哪些难点？"},{"url":"https://www.zhihu.com/question/1888628372260774392","title":"加沙爆发反战示威，参与民众要求哈马斯武装离开加沙，具体情况如何？这样的局面是什么导致的？"},{"url":"https://www.zhihu.com/question/661609913","title":"同样是西虹市有钱人，《西虹市首富》里的王多鱼和《抓娃娃》里的马成钢谁更有钱？"},{"url":"https://www.zhihu.com/question/15595836704","title":"如果编撰中国网文史，哪些人和事是必须提及的？"},{"url":"https://www.zhihu.com/question/15738564300","title":"美国政府将 50 余家中国科技公司列入「实体清单」，会带来哪些影响？"},{"url":"https://www.zhihu.com/question/1888504919339792145","title":"17 岁代孕女孩产下双胞胎已上户口，五旬男子或让女孩假装其妻子办理出生证明，暴露出了哪些问题？"},{"url":"https://www.zhihu.com/question/1888865082525574989","title":"公司回应「要求员工每月加班 10 晚以上」，称可帮缴社保个人部分，这样做合法吗？你会接受这种加班吗？"},{"url":"https://www.zhihu.com/question/15747764785","title":"苹果宣布向浙大捐赠 3000 万元人民币，支持编程教育，怎样解读苹果这一动作？为什么选择浙大？"},{"url":"https://www.zhihu.com/question/15727122034","title":"《乘风 2025》李晟以断层票数登顶第一，反超王珞丹、叶童等热门选手，如何评价她的表现？"},{"url":"https://www.zhihu.com/question/15056012615","title":"为什么山西冷得和东北一样程度？"},{"url":"https://www.zhihu.com/question/1888520368077127816","title":"卫健委新规强制要求预包装食品标注饱和脂肪（酸）和糖，并提示儿童青少年避免摄入过量盐油糖，具有哪些意义？"},{"url":"https://www.zhihu.com/question/15645883096","title":"男子 200 多万买二手房遇「20 年租约」，该找谁追责？租约比买卖合同更有效吗？如何查房屋出租情况？"},{"url":"https://www.zhihu.com/question/15582295443","title":"很多成年人接触健身之后才发现「腹式呼吸」很重要，但学校体育课为什么不从一开始就教孩子练腹式呼吸呢？"},{"url":"https://www.zhihu.com/question/437165912","title":"Steam 上有什么感人至深的游戏？"},{"url":"https://www.zhihu.com/question/15062142537","title":"你的春天是什么温度，可以用照片来表达吗？"},{"url":"https://www.zhihu.com/question/1888580413204685344","title":"香飘飘新品奶茶卖 16 元一杯，含明前特级龙井，你能接受这个价位吗？有必要用特级龙井做奶茶吗？"},{"url":"https://www.zhihu.com/question/1888553119216035519","title":"如何评价《鸣潮》2.2 版本中卡提希娅的主线剧情？"},{"url":"https://www.zhihu.com/question/1887084947031949693","title":"在游戏中，自己伤害增加 25% 和敌人受到伤害增加 25%，哪个好？"},{"url":"https://www.zhihu.com/question/1888573522948891336","title":"Google 调整 Android 开源政策，核心开发全面转向私有分支，这将对行业产生什么影响？"},{"url":"https://www.zhihu.com/question/14159370972","title":"人类明明是顶级杂食动物，胃酸接近食腐动物，为什么连生肉都不敢吃？"},{"url":"https://www.zhihu.com/question/15676470786","title":"雷军重回母校武汉大学，你觉得他此行是「校友情怀」还是「战略布局」？"},{"url":"https://www.zhihu.com/question/10242455751","title":"如果你是老板，面对「能说会道」、「踏实稳重」、「聪明伶俐」三类员工，你会优先淘汰哪一类？"},{"url":"https://www.zhihu.com/question/14620432955","title":"领导总是公开批评我，私下总是夸赞我，这是什么意思？"},{"url":"https://www.zhihu.com/question/437033682","title":"《星球大战》前传中，议长宣布共和国改帝国，为什么没有人反对呢，而是一片欢呼呢？"},{"url":"https://www.zhihu.com/question/15447851308","title":"评价电视剧《雁回时》?"},{"url":"https://www.zhihu.com/question/1885633584972399746","title":"为啥《火影忍者》已经完结十多年了，还有如此高的热度？"},{"url":"https://www.zhihu.com/question/1888202911982527953","title":"如何评价知名网络主播「甲亢哥」Speed 于 3 月 26 日在北京的直播？"},{"url":"https://www.zhihu.com/question/15238304263","title":"网传苹果将出超薄新版手机，iPhone 17 Air 或是苹果首款无端口手机，这一改变有哪些意义？"},{"url":"https://www.zhihu.com/question/15673604861","title":"如何看待蔚来 CEO 李斌在最新沟通会称「四季度必须盈利」？若未达成会对蔚来产生哪些影响？"},{"url":"https://www.zhihu.com/question/15750330696","title":"山姆试吃员晒工资条被开除，公司回应「双方签了保密协议，薪资发放符合规定」，怎样从法律角度解读？"},{"url":"https://www.zhihu.com/question/1887761907844372478","title":"农民工中午吃饭为什么都喜欢喝一瓶啤酒呢？"},{"url":"https://www.zhihu.com/question/15749926709","title":"如何评价《鸣潮》2.2 版本新主线剧情？"},{"url":"https://www.zhihu.com/question/1888721154203694629","title":"如何评价《一人之下》第 710（752）话？"},{"url":"https://www.zhihu.com/question/1887966798441325936","title":"如何评价 3 月 25 日开启预售的领克 900，预售价 33 万起，预售 24 小时订单破 14600 台?"},{"url":"https://www.zhihu.com/question/15739126811","title":"德国新一届联邦议院成立，朔尔茨政府解散，新政府会有哪些变化？对德国政坛有哪些影响？"},{"url":"https://www.zhihu.com/question/15714784930","title":"下半场反击未果，中国男足 0-2 负于澳大利亚，塞尔吉尼奥下半场替补登场，如何评价本场比赛？"},{"url":"https://www.zhihu.com/question/15754935409","title":"如何评价电视剧《黄雀》大结局？"},{"url":"https://www.zhihu.com/question/1888573596114338420","title":"3 月 27 日的任天堂直面会上有哪些值得期待的游戏？"},{"url":"https://www.zhihu.com/question/1888565008272700194","title":"如何评价 Google 宣布停止 Android 开源项目 AOSP?"},{"url":"https://www.zhihu.com/question/15701732460","title":"小米 SU7 Ultra 超速撞飞电动车事件引发热议，随着大马力新能源车普及，如何平衡性能与安全驾驶？"},{"url":"https://www.zhihu.com/question/431139498","title":"德川家康除了活得久之外还有什么独特才能?"},{"url":"https://www.zhihu.com/question/14330182052","title":"如何评价《BanG Dream! Ave Mujica》最终话？"},{"url":"https://www.zhihu.com/question/13590791982","title":"如何评价《BanG Dream! Ave Mujica》第十三集？"}]